tendril/__init__.py
tendril/entities/__init__.py
tendril/entities/base.py
tendril_entities_base-0.1.2.dist-info/DESCRIPTION.rst
tendril_entities_base-0.1.2.dist-info/METADATA
tendril_entities_base-0.1.2.dist-info/RECORD
tendril_entities_base-0.1.2.dist-info/WHEEL
tendril_entities_base-0.1.2.dist-info/metadata.json
tendril_entities_base-0.1.2.dist-info/top_level.txt
