Metadata-Version: 2.0
Name: tendril-entities-base
Version: 0.1.2
Summary: Tendril Entity Primitives
Home-page: https://github.com/chintal/tendril-entity-base
Author: Chintalagiri Shashank
Author-email: shashank@chintal.in
License: AGPLv3
Keywords: tendril
Platform: UNKNOWN
Classifier: Development Status :: 4 - Beta
Classifier: Natural Language :: English
Classifier: Programming Language :: Python
